browse_to_test/__init__.py
browse_to_test/ai/__init__.py
browse_to_test/ai/factory.py
browse_to_test/ai/unified.py
browse_to_test/core/__init__.py
browse_to_test/core/config.py
browse_to_test/core/executor.py
browse_to_test/core/orchestration/__init__.py
browse_to_test/core/orchestration/session.py
browse_to_test/core/processing/__init__.py
browse_to_test/core/processing/action_analyzer.py
browse_to_test/core/processing/context_collector.py
browse_to_test/core/processing/input_parser.py
browse_to_test/core/utils/__init__.py
browse_to_test/core/utils/comment_manager.py
browse_to_test/core/utils/language_templates.py
browse_to_test/output_langs/__init__.py
browse_to_test/output_langs/exceptions.py
browse_to_test/output_langs/manager.py
browse_to_test/output_langs/registry.py
browse_to_test/output_langs/common/constants.json
browse_to_test/output_langs/common/messages.json
browse_to_test/output_langs/common/patterns.json
browse_to_test/output_langs/generated/__init__.py
browse_to_test/output_langs/generated/constants.py
browse_to_test/output_langs/generated/exceptions.py
browse_to_test/output_langs/generated/imports.py
browse_to_test/output_langs/generated/utilities.py
browse_to_test/output_langs/javascript/__init__.py
browse_to_test/output_langs/javascript/metadata.json
browse_to_test/output_langs/javascript/generators/__init__.py
browse_to_test/output_langs/javascript/generators/playwright_generator.py
browse_to_test/output_langs/python/__init__.py
browse_to_test/output_langs/python/metadata.json
browse_to_test/output_langs/python/generators/__init__.py
browse_to_test/output_langs/python/generators/playwright_generator.py
browse_to_test/output_langs/python/generators/selenium_generator.py
browse_to_test/output_langs/python/templates/base_imports.txt
browse_to_test/output_langs/python/templates/exception_classes.txt
browse_to_test/output_langs/python/templates/utility_functions.txt
browse_to_test/output_langs/typescript/__init__.py
browse_to_test-0.2.19.dist-info/METADATA
browse_to_test-0.2.19.dist-info/WHEEL
browse_to_test-0.2.19.dist-info/entry_points.txt
browse_to_test-0.2.19.dist-info/top_level.txt
browse_to_test-0.2.19.dist-info/RECORD
